higlass/__init__.py
higlass/_display.py
higlass/_scale.py
higlass/_utils.py
higlass/api.py
higlass/tilesets.py
higlass/fuse/__init__.py
higlass/fuse/_httpfs.py
higlass/server/__init__.py
higlass/server/_background_server.py
higlass/server/_provider.py
higlass-0.0.1.dist-info/METADATA
higlass-0.0.1.dist-info/WHEEL
higlass-0.0.1.dist-info/licenses/LICENSE
higlass-0.0.1.dist-info/RECORD
